afdd/__init__.py
afdd/apar.py
afdd-0.0.1.dist-info/METADATA
afdd-0.0.1.dist-info/WHEEL
afdd-0.0.1.dist-info/licenses/LICENSE
afdd-0.0.1.dist-info/RECORD
