Metadata-Version: 2.1
Name: afdd
Version: 0.0.1
Summary: A python package for automated fault detection and diagnosis
Project-URL: Homepage, https://github.com/RobertoChiosa/afdd
Project-URL: Bug Tracker, https://github.com/RobertoChiosa/afdd/issues
Author-email: Roberto Chiosa <roberto.chiosa@polito.it>
License-File: LICENSE
Classifier: License :: OSI Approved :: MIT License
Classifier: Operating System :: OS Independent
Classifier: Programming Language :: Python :: 3
Requires-Python: >=3.7
